.coveragerc
.gitignore
.travis.yml
LICENSE
MANIFEST.in
README.md
setup.py
tox.ini
schema_migrations/__init__.py
schema_migrations.egg-info/PKG-INFO
schema_migrations.egg-info/SOURCES.txt
schema_migrations.egg-info/dependency_links.txt
schema_migrations.egg-info/requires.txt
schema_migrations.egg-info/top_level.txt
tests/test_schema_migrations.py
tests/migrations/0001-initial/forward.sql
tests/migrations/0002-add-gender/forward.sql