Metadata-Version: 1.0
Name: schema-migrations
Version: 0.2
Summary: PostgreSQL Schema Migrations
Home-page: https://github.com/dmonroy/schema-migrations
Author: Darwin Monroy
Author-email: contact@darwinmonroy.com
License: MIT License
Platform: UNKNOWN
